{
  "title": "Thèm ăn đất, bột sắn (pica) khi mang thai",
  "slug": "pica-khi-mang-thai",
  "excerpt": "Ăn vật không dinh dưỡng có thể báo hiệu thiếu sắt. Cần khám và xét nghiệm — ACOG, NHS.",
  "category": "truoc-sinh",
  "tags": [
    "pica",
    "sat",
    "trieu-chung"
  ],
  "reviewer": "Tham chiếu ACOG, NHS",
  "publishedAt": "2026-05-16T10:00:00+07:00",
  "updatedAt": "2026-05-31T08:00:00+07:00",
  "metaTitle": "Pica khi mang thai | Blog Bầu Ăn Gì?",
  "metaDescription": "Thèm ăn đất, bột sắn thai kỳ — ACOG, NHS.",
  "sourceReferences": [
    {
      "title": "ACOG — Nutrition During Pregnancy",
      "url": "https://www.acog.org/womens-health/faqs/nutrition-during-pregnancy",
      "publisher": "ACOG",
      "accessedAt": "2026-05-31"
    },
    {
      "title": "NHS — Pica in pregnancy",
      "url": "https://www.nhs.uk/pregnancy/related-conditions/common-symptoms/unusual-cravings/",
      "publisher": "NHS",
      "accessedAt": "2026-05-31"
    }
  ],
  "content": "## Pica là gì?\n\nThèm ăn vật không phải thực phẩm: đất, bột sắn, băng giấy, băng keo.\n\n## Nguy cơ\n\nNhiễm khuẩn, chì, thiếu dinh dưỡng; có thể liên quan thiếu sắt.\n\n## Việc nên làm\n\n- Nói với bác sĩ **không xấu hổ**.\n- Xét nghiệm sắt, vi chất.\n- Không tự ăn đất/bột sắn “theo kinh nghiệm”.",
  "readingTimeMinutes": 5,
  "status": "published",
  "author": "Đội ngũ Bầu Ăn Gì?"
}
