{
  "readingTimeMinutes": 5,
  "status": "published",
  "author": "Đội ngũ Bầu Ăn Gì?",
  "title": "Sức khỏe răng miệng khi mang thai",
  "slug": "suc-khoe-rang-mieng-khi-mang-thai",
  "excerpt": "Viêm nướu có thể liên quan sinh non nếu không điều trị. Khám nha khoa an toàn và vệ sinh răng — NHS, ACOG.",
  "category": "truoc-sinh",
  "tags": [
    "rang-mieng",
    "kham-thai"
  ],
  "reviewer": "Tham chiếu NHS, ACOG",
  "publishedAt": "2026-05-24T09:00:00+07:00",
  "updatedAt": "2026-05-31T08:00:00+07:00",
  "metaTitle": "Răng miệng khi mang thai | Blog Bầu Ăn Gì?",
  "metaDescription": "Chăm răng khi mang thai, khám nha an toàn — NHS, ACOG.",
  "sourceReferences": [
    {
      "title": "NHS — Bleeding gums in pregnancy",
      "url": "https://www.nhs.uk/pregnancy/related-conditions/common-symptoms/bleeding-gums/",
      "publisher": "NHS",
      "accessedAt": "2026-05-31"
    },
    {
      "title": "ACOG — Oral Health Care During Pregnancy",
      "url": "https://www.acog.org/clinical/clinical-guidance/committee-opinion/articles/2013/08/oral-health-care-during-pregnancy-and-through-the-lifespan",
      "publisher": "ACOG",
      "accessedAt": "2026-05-31"
    }
  ],
  "content": "## Thay đổi khi mang thai\n\nNướu dễ chảy máu, viêm hơn do hormone. Một số nghiên cứu liên hệ bệnh nha khoa chưa điều trị với biến chứng thai kỳ — nên chăm sóc sớm.\n\n## Việc nên làm\n\n- Đánh răng 2 lần/ngày, chỉ nướu bằng fluor.\n- Khám nha **báo đang mang thai**; nhiều thủ thuật an toàn.\n- Hạn chế đồ ngọt dính răng.\n\n## Thuốc gây tê\n\nAn toàn trong nha khoa khi do bác sĩ thực hiện; thông báo tuần thai.\n\n## Khẩn cấp\n\nSưng nướu/sáng miệng, sốt — khám ngay."
}
