{
  "slug": "tiem-vitamin-k-cho-tre-so-sinh",
  "title": "Vitamin K injection for newborns: what parents should know",
  "excerpt": "Why vitamin K prevents bleeding, standard newborn dosing, and breastfeeding compatibility — Medlatec, CDC.",
  "content": "## Why vitamin K?\n\nNewborns have low vitamin K stores and higher risk of **vitamin K deficiency bleeding (VKDB)**.\n\n## After birth\n\nMany countries recommend an **early intramuscular vitamin K dose** per local protocol—highly effective prevention.\n\n## Breastfeeding\n\nBreast milk remains recommended; the injection **supplements** breastfeeding.\n\n## Note\n\nFollow hospital newborn protocols; do not self-inject at home without medical direction.",
  "metaTitle": "Newborn vitamin K shot | Bầu Ăn Gì? Blog",
  "metaDescription": "Vitamin K for newborns — Medlatec, CDC.",
  "author": "Bầu Ăn Gì? Team",
  "reviewer": "References Medlatec, CDC"
}
