{
  "slug": "uong-nuoc-khi-mang-thai",
  "title": "Hydration during pregnancy",
  "excerpt": "Why fluids matter, practical intake habits, dehydration signs, and drinks to limit — especially in hot climates.",
  "content": "## Role of water\n\nSupports blood volume, amniotic fluid, digestion, and temperature control. Needs rise in pregnancy and breastfeeding.\n\n## How to drink\n\n- Sip through the day; more in heat and after exercise.\n- Many clinicians suggest roughly **8–12 cups (2–3 L)** total fluids daily — individual needs vary.\n- Water, soup, milk count; limit sugary soda.\n\n## Signs of dehydration\n\nDark urine, dizziness, headache, cramping — increase fluids and seek care if severe.\n\n## Limit\n\nExcess caffeine, alcohol, unpasteurized beverages of unknown origin.",
  "metaTitle": "Drinking water during pregnancy | Bầu Ăn Gì? Blog",
  "metaDescription": "How much water to drink in pregnancy, dehydration signs, and what to avoid.",
  "author": "Bầu Ăn Gì? Team",
  "reviewer": "References ACOG, NHS"
}
